<annotation>
	<folder>csgo screenshots</folder>
	<filename>de_dust0569.jpg</filename>
	<path>C:\Users\HOME\Desktop\csgo screenshots\de_dust0569.jpg</path>
	<source>
		<database>Unknown</database>
	</source>
	<size>
		<width>1920</width>
		<height>1080</height>
		<depth>3</depth>
	</size>
	<segmented>0</segmented>
	<object>
		<name>t</name>
		<pose>Unspecified</pose>
		<truncated>0</truncated>
		<difficult>0</difficult>
		<bndbox>
			<xmin>702</xmin>
			<ymin>527</ymin>
			<xmax>777</xmax>
			<ymax>726</ymax>
		</bndbox>
	</object>
	<object>
		<name>th</name>
		<pose>Unspecified</pose>
		<truncated>0</truncated>
		<difficult>0</difficult>
		<bndbox>
			<xmin>727</xmin>
			<ymin>530</ymin>
			<xmax>756</xmax>
			<ymax>559</ymax>
		</bndbox>
	</object>
	<object>
		<name>c</name>
		<pose>Unspecified</pose>
		<truncated>0</truncated>
		<difficult>0</difficult>
		<bndbox>
			<xmin>1124</xmin>
			<ymin>533</ymin>
			<xmax>1161</xmax>
			<ymax>605</ymax>
		</bndbox>
	</object>
	<object>
		<name>ch</name>
		<pose>Unspecified</pose>
		<truncated>0</truncated>
		<difficult>0</difficult>
		<bndbox>
			<xmin>1129</xmin>
			<ymin>531</ymin>
			<xmax>1149</xmax>
			<ymax>551</ymax>
		</bndbox>
	</object>
</annotation>
